timeback_oneroster/__init__.py
timeback_oneroster/client.py
timeback_oneroster/constants.py
timeback_oneroster/exceptions.py
timeback_oneroster/py.typed
timeback_oneroster/utils.py
timeback_oneroster/lib/__init__.py
timeback_oneroster/lib/filter.py
timeback_oneroster/lib/pagination.py
timeback_oneroster/lib/params.py
timeback_oneroster/lib/transport.py
timeback_oneroster/resources/__init__.py
timeback_oneroster/resources/base.py
timeback_oneroster/resources/assessment/__init__.py
timeback_oneroster/resources/assessment/line_items.py
timeback_oneroster/resources/assessment/results.py
timeback_oneroster/resources/gradebook/__init__.py
timeback_oneroster/resources/gradebook/categories.py
timeback_oneroster/resources/gradebook/line_items.py
timeback_oneroster/resources/gradebook/results.py
timeback_oneroster/resources/gradebook/score_scales.py
timeback_oneroster/resources/resources/__init__.py
timeback_oneroster/resources/resources/resources.py
timeback_oneroster/resources/rostering/__init__.py
timeback_oneroster/resources/rostering/academic_sessions.py
timeback_oneroster/resources/rostering/classes.py
timeback_oneroster/resources/rostering/courses.py
timeback_oneroster/resources/rostering/demographics.py
timeback_oneroster/resources/rostering/enrollments.py
timeback_oneroster/resources/rostering/orgs.py
timeback_oneroster/resources/rostering/schools.py
timeback_oneroster/resources/rostering/users.py
timeback_oneroster/types/__init__.py
timeback_oneroster/types/assessment.py
timeback_oneroster/types/base.py
timeback_oneroster/types/gradebook.py
timeback_oneroster/types/input.py
timeback_oneroster/types/resources.py
timeback_oneroster/types/rostering.py
timeback_oneroster-0.1.4.dist-info/METADATA
timeback_oneroster-0.1.4.dist-info/WHEEL
timeback_oneroster-0.1.4.dist-info/RECORD
